metdatapy/__init__.py
metdatapy/cli.py
metdatapy/core.py
metdatapy/derive.py
metdatapy/io.py
metdatapy/manifest.py
metdatapy/mapper.py
metdatapy/mlprep.py
metdatapy/qc.py
metdatapy/units.py
metdatapy/utils.py
metdatapy-1.0.0.dist-info/licenses/LICENSE
metdatapy-1.0.0.dist-info/METADATA
metdatapy-1.0.0.dist-info/WHEEL
metdatapy-1.0.0.dist-info/entry_points.txt
metdatapy-1.0.0.dist-info/top_level.txt
metdatapy-1.0.0.dist-info/RECORD
