Metadata-Version: 2.4
Name: metdatapy
Version: 1.0.0
Summary: Source-agnostic toolkit for ingesting, cleaning, QC, and preparing meteorological time-series data for ML.
Author: Kyriakos Kartas
License: MIT
Project-URL: homepage, https://github.com/kkartas/MetDataPy
Requires-Python: >=3.9
License-File: LICENSE
Requires-Dist: pandas>=2.0
Requires-Dist: numpy>=1.23
Requires-Dist: pyarrow>=13.0
Requires-Dist: click>=8.1
Requires-Dist: pydantic>=2.4
Requires-Dist: PyYAML>=6.0
Provides-Extra: ml
Requires-Dist: scikit-learn>=1.2; extra == "ml"
Requires-Dist: statsmodels>=0.13; extra == "ml"
Provides-Extra: netcdf
Requires-Dist: xarray>=2023.6.0; extra == "netcdf"
Requires-Dist: netCDF4>=1.6; extra == "netcdf"
Requires-Dist: cftime>=1.6; extra == "netcdf"
Provides-Extra: extras
Requires-Dist: astral>=3.2; extra == "extras"
Requires-Dist: holidays>=0.36; extra == "extras"
Provides-Extra: viz
Requires-Dist: matplotlib>=3.5; extra == "viz"
Requires-Dist: seaborn>=0.12; extra == "viz"
Provides-Extra: all
Requires-Dist: scikit-learn>=1.2; extra == "all"
Requires-Dist: statsmodels>=0.13; extra == "all"
Requires-Dist: xarray>=2023.6.0; extra == "all"
Requires-Dist: netCDF4>=1.6; extra == "all"
Requires-Dist: cftime>=1.6; extra == "all"
Requires-Dist: astral>=3.2; extra == "all"
Requires-Dist: holidays>=0.36; extra == "all"
Requires-Dist: matplotlib>=3.5; extra == "all"
Requires-Dist: seaborn>=0.12; extra == "all"
Dynamic: license-file
